dubhe_sdk/__init__.py
dubhe_sdk/config.py
dubhe_sdk/http_server.py
dubhe_sdk/tcp_server.py
dubhe_sdk/param/__init__.py
dubhe_sdk/param/base_param.py
dubhe_sdk/param/inference_param.py
dubhe_sdk/param/predict_param.py
dubhe_sdk/param/train_param.py
dubhe_sdk/service/ADCkafka.py
dubhe_sdk/service/Logger.py
dubhe_sdk/service/__init__.py
dubhe_sdk/service/context.py
dubhe_sdk/service/dataset.py
dubhe_sdk/service/out_dataset.py
dubhe_sdk/service/run.py
dubhe_sdk/service/service_prepare.py
dubhe_sdk-2.14.dist-info/LICENSE
dubhe_sdk-2.14.dist-info/METADATA
dubhe_sdk-2.14.dist-info/WHEEL
dubhe_sdk-2.14.dist-info/top_level.txt
dubhe_sdk-2.14.dist-info/zip-safe
dubhe_sdk-2.14.dist-info/RECORD
