Metadata-Version: 2.1
Name: dubhe-sdk
Version: 2.14
Summary: TCL AI platform, algorithm software development kit
Home-page: https://github.com/hathawayhh/dubhe-sdk
Author: huanghui
Author-email: 
License: MIT
Keywords: dubhe
License-File: LICENSE
Requires-Dist: Flask (==1.1.1)
Requires-Dist: kafka-python (==2.0.1)
